colmena/__init__.py
colmena/exceptions.py
colmena/proxy.py
colmena/py.typed
colmena/version.py
colmena/models/__init__.py
colmena/models/methods.py
colmena/models/results.py
colmena/queue/__init__.py
colmena/queue/base.py
colmena/queue/python.py
colmena/queue/redis.py
colmena/queue/tests/test_base.py
colmena/queue/tests/test_queues.py
colmena/task_server/__init__.py
colmena/task_server/base.py
colmena/task_server/globus.py
colmena/task_server/local.py
colmena/task_server/parsl.py
colmena/task_server/tests/__init__.py
colmena/task_server/tests/test_base.py
colmena/task_server/tests/test_globus.py
colmena/task_server/tests/test_local.py
colmena/task_server/tests/test_parsl.py
colmena/task_server/tests/test_retry.py
colmena/tests/conftest.py
colmena/tests/test_model.py
colmena/tests/test_proxy.py
colmena/tests/test_task_model.py
colmena/thinker/__init__.py
colmena/thinker/resources.py
colmena/thinker/tests/test_resources.py
colmena/thinker/tests/test_thinker.py
colmena-0.7.2.dist-info/licenses/LICENSE.txt
colmena-0.7.2.dist-info/METADATA
colmena-0.7.2.dist-info/WHEEL
colmena-0.7.2.dist-info/top_level.txt
colmena-0.7.2.dist-info/RECORD
