Metadata-Version: 2.4
Name: colmena
Version: 0.7.2
Summary: colmena: Intelligent Steerable Pipelines on HPC
Author-email: Globus Labs <labs@globus.org>, Logan Ward <lward@anl.gov>, Greg Pauloski <jgpauloski@uchicago.edu>, Yadu Babuji <yadudoc1729@gmail.com>
License: 
Project-URL: repository, https://github.com/exalearn/colmena
Project-URL: documentation, https://colmena.readthedocs.io/
Keywords: HPC,AI,Workflows
Classifier: Development Status :: 4 - Beta
Classifier: Intended Audience :: Science/Research
Classifier: License :: OSI Approved :: Apache Software License
Classifier: Natural Language :: English
Classifier: Operating System :: OS Independent
Classifier: Topic :: System :: Distributed Computing
Classifier: Programming Language :: Python :: 3
Classifier: Topic :: Scientific/Engineering
Requires-Python: >=3.9
License-File: LICENSE.txt
Requires-Dist: parsl>=2022
Requires-Dist: pydantic<3,>=2
Requires-Dist: redis>=4.3
Requires-Dist: proxystore>=0.5.0
Provides-Extra: globus
Requires-Dist: globus-compute-sdk>=1.0.5; extra == "globus"
Provides-Extra: test
Requires-Dist: flake8; extra == "test"
Requires-Dist: pytest; extra == "test"
Requires-Dist: pytest-timeout; extra == "test"
Requires-Dist: pytest-mock; extra == "test"
Requires-Dist: pytest-repeat; extra == "test"
Requires-Dist: pytest-cov; extra == "test"
Dynamic: license-file
